{"algorithms_index.md":"h0QK8oYC","daily_python在多用户环境安装依赖.md":"ZLB1EH72","daily_font和glyph的关系.md":"z7b4amZU","daily_2023年年终总结.md":"flesBiX2","daily_index.md":"5lyXsdLl","api-examples.md":"cE1CCd8a","daily_非常实用的26个prompt小技巧.md":"WZrXH_CM","algorithms_前端面试题：数组扁平化、去重、排序.md":"kNpBZOhs","daily_fontface的使用.md":"j6MZNh0t","daily_git_submodules（git子模块）.md":"pHvDr2N6","daily_python使用selenium抓取网页动态内容.md":"MqoIocjm","daily_记录一次docker部署目标服务器脚本.md":"g_4cb7VI","algorithms_文档协同编辑能力-ot算法.md":"e4mxfqhl","daily_解析msoffice_word有序列表样式.md":"g6wdJizC","markdown-examples.md":"vrkppzw5","reader_index.md":"SJx6DvXv","index.md":"XNCLZG1F","reader_reader-2023.md":"YL5ey6yq","marks_2024.md":"PL_fOIzy","daily_记录一次docker服务部署.md":"09gw9-Xa","todolist_2024.md":"6xjqOmv2","daily_网络：17.0.0.1和localhost以及0.0.0.0的区别.md":"9_yKhssm","daily_搭配google_gemini能力实现一个终端ai_cli助手.md":"5pxBxmaz"}
